klab/__init__.py
klab/engine.py
klab/exceptions.py
klab/geometry.py
klab/klab.py
klab/observable.py
klab/observation.py
klab/references.py
klab/ticket.py
klab/types.py
klab/utils.py
klab_client_py-0.1.2.dist-info/WHEEL
klab_client_py-0.1.2.dist-info/METADATA
klab_client_py-0.1.2.dist-info/licenses/LICENSE
klab_client_py-0.1.2.dist-info/RECORD
