Metadata-Version: 2.1
Name: klab-client-py
Version: 0.1.2
Summary: Python client to interact with a running k.LAB Engine.
License: AGPLv3
Author: Ferdinando Villa,Andrea Antonello
Requires-Python: >=3.8
Classifier: Development Status :: 4 - Beta
Classifier: Programming Language :: Python
Requires-Dist: requests>=2.28.2
Project-URL: homepage, https://integratedmodelling.org/
Project-URL: repository, https://github.com/integratedmodelling/klab-client-python.git
